s3vectors/__init__.py
s3vectors/__version__.py
s3vectors/cli.py
s3vectors/commands/__init__.py
s3vectors/commands/embed_put.py
s3vectors/commands/embed_query.py
s3vectors/core/__init__.py
s3vectors/core/services.py
s3vectors/core/streaming_batch_orchestrator.py
s3vectors/core/unified_processor.py
s3vectors/utils/__init__.py
s3vectors/utils/boto_config.py
s3vectors/utils/config.py
s3vectors/utils/models.py
s3vectors/utils/multimodal_helpers.py
s3vectors_embed_cli-0.2.1.dist-info/licenses/LICENSE
s3vectors_embed_cli-0.2.1.dist-info/licenses/NOTICE
s3vectors_embed_cli-0.2.1.dist-info/METADATA
s3vectors_embed_cli-0.2.1.dist-info/WHEEL
s3vectors_embed_cli-0.2.1.dist-info/entry_points.txt
s3vectors_embed_cli-0.2.1.dist-info/top_level.txt
s3vectors_embed_cli-0.2.1.dist-info/RECORD
