Metadata-Version: 2.4
Name: s3vectors-embed-cli
Version: 0.2.1
Summary: Standalone CLI for S3 Vector operations with Bedrock embeddings
Home-page: https://github.com/awslabs/s3vectors-embed-cli
Author: Vaibhav Sabharwal
Author-email: Vaibhav Sabharwal <vsabhar@amazon.com>
Maintainer: Vaibhav Sabharwal
Maintainer-email: Vaibhav Sabharwal <vsabhar@amazon.com>
License: 
Project-URL: Homepage, https://github.com/awslabs/s3vectors-embed-cli
Project-URL: Repository, https://github.com/awslabs/s3vectors-embed-cli
Project-URL: Issues, https://github.com/awslabs/s3vectors-embed-cli/issues
Project-URL: Documentation, https://github.com/awslabs/s3vectors-embed-cli#readme
Project-URL: Source, https://github.com/awslabs/s3vectors-embed-cli
Keywords: aws,s3,vectors,embeddings,bedrock,cli,machine-learning,ai
Classifier: Development Status :: 4 - Beta
Classifier: Intended Audience :: Developers
Classifier: Intended Audience :: System Administrators
Classifier: License :: OSI Approved :: Apache Software License
Classifier: Operating System :: OS Independent
Classifier: Programming Language :: Python :: 3
Classifier: Programming Language :: Python :: 3.9
Classifier: Programming Language :: Python :: 3.10
Classifier: Programming Language :: Python :: 3.11
Classifier: Programming Language :: Python :: 3.12
Classifier: Topic :: Software Development :: Libraries :: Python Modules
Classifier: Topic :: System :: Systems Administration
Classifier: Topic :: Utilities
Classifier: Topic :: Scientific/Engineering :: Artificial Intelligence
Classifier: Environment :: Console
Requires-Python: >=3.9
License-File: LICENSE
License-File: NOTICE
Requires-Dist: boto3>=1.39.5
Requires-Dist: botocore>=1.39.5
Requires-Dist: click>=8.0.0
Requires-Dist: rich>=12.0.0
Requires-Dist: pydantic>=1.10.0
Dynamic: author
Dynamic: home-page
Dynamic: license-file
Dynamic: maintainer
Dynamic: requires-python
